ehh/__init__.py
ehh/cli.py
ehh-1.1.1.dist-info/METADATA
ehh-1.1.1.dist-info/WHEEL
ehh-1.1.1.dist-info/entry_points.txt
ehh-1.1.1.dist-info/top_level.txt
ehh-1.1.1.dist-info/RECORD
